logging_context/__init__.py
logging_context/formatter.py
logging_context/helpers.py
logging_context/context/__init__.py
logging_context/context/base.py
logging_context/context/threadlocal.py
logging_context-0.1.0.dist-info/LICENSE
logging_context-0.1.0.dist-info/METADATA
logging_context-0.1.0.dist-info/WHEEL
logging_context-0.1.0.dist-info/top_level.txt
logging_context-0.1.0.dist-info/RECORD
