Metadata-Version: 2.1
Name: logging-context
Version: 0.1.0
Summary: Python Logging Context
Home-page: https://github.com/vuonglv1612/logging-context
Author: vuonglv
License: UNKNOWN
Platform: UNKNOWN
License-File: LICENSE
Provides-Extra: dev
Requires-Dist: pytest ; extra == 'dev'
Requires-Dist: coverage ; extra == 'dev'
Requires-Dist: pytest-cov ; extra == 'dev'
Requires-Dist: codecov ; extra == 'dev'
Requires-Dist: darker ; extra == 'dev'
Requires-Dist: black ; extra == 'dev'
Requires-Dist: isort ; extra == 'dev'
Requires-Dist: pylint ; extra == 'dev'
Requires-Dist: mypy ; extra == 'dev'
Requires-Dist: gitchangelog ; extra == 'dev'
